wowhmm/__init__.py
wowhmm/core.py
wowhmm-0.1.5.dist-info/METADATA
wowhmm-0.1.5.dist-info/WHEEL
wowhmm-0.1.5.dist-info/top_level.txt
wowhmm-0.1.5.dist-info/RECORD
