Metadata-Version: 2.1
Name: wowhmm
Version: 0.1.5
Summary: Who owes whom how much money
Home-page: https://github.com/yoonthegoon/wowhmm
Requires-Dist: pandas ==2.2.2
